external_deps/__init__.py
external_deps/builder.py
external_deps/cuda.py
external_deps/mumps.py
external_deps/p4est.py
external_deps/pangulu.py
external_deps/source_downloader.py
fealpy/__init__.py
fealpy/functional.py
fealpy/logs.py
fealpy/typing.py
fealpy/backend/__init__.py
fealpy/backend/base.py
fealpy/backend/cupy_backend.py
fealpy/backend/jax_backend.py
fealpy/backend/manager.py
fealpy/backend/manager.pyi
fealpy/backend/manager_old.pyi
fealpy/backend/mindspore_backend.py
fealpy/backend/numpy_api.py
fealpy/backend/numpy_backend.py
fealpy/backend/paddle_backend.py
fealpy/backend/pytorch_backend.py
fealpy/backend/taichi_backend.py
fealpy/backend/array_api_standard/__init__.py
fealpy/backend/array_api_standard/api_2023_12.py
fealpy/cdo/__init__.py
fealpy/cem/__init__.py
fealpy/cem/em_fdtd_sim.py
fealpy/cem/pml_polar_fe_model.py
fealpy/cem/generator/__init__.py
fealpy/cem/generator/eit_data_generator.py
fealpy/cem/generator/laplace_data_generator.py
fealpy/cgp/__init__.py
fealpy/cgp/model/__init__.py
fealpy/cgraph/__init__.py
fealpy/cgraph/base.py
fealpy/cgraph/functionspace.py
fealpy/cgraph/graph.py
fealpy/cgraph/solver.py
fealpy/cgraph/mesh/__init__.py
fealpy/cgraph/mesh/creation.py
fealpy/cgraph/mesh/ops.py
fealpy/common/DynamicArray.py
fealpy/common/Tools.py
fealpy/common/__init__.py
fealpy/common/tensor.py
fealpy/csm/__init__.py
fealpy/csm/afem_phase_field_crack_hybrid_mix_model.py
fealpy/csm/afem_phase_field_crack_propagation_problem.py
fealpy/csm/afem_phase_field_crack_propagation_problem_2d.py
fealpy/csm/beam_truss.py
fealpy/csm/fracture_damage_integrator.py
fealpy/csm/ipfem_phase_field_crack_hybrid_mix_model.py
fealpy/csm/mfront.py
fealpy/decorator/__init__.py
fealpy/decorator/coordinates.py
fealpy/decorator/input_produce.py
fealpy/decorator/variantmethod.py
fealpy/fdm/__init__.py
fealpy/fdm/convection_operator.py
fealpy/fdm/diffusion_operator.py
fealpy/fdm/dirichlet_bc.py
fealpy/fdm/elliptic_fdm_model.py
fealpy/fdm/hyperbolic_fdm_model.py
fealpy-3.3.2.dist-info/METADATA
fealpy-3.3.2.dist-info/WHEEL
fealpy-3.3.2.dist-info/top_level.txt
fealpy-3.3.2.dist-info/RECORD
