Metadata-Version: 2.4
Name: fealpy
Version: 3.3.2
Summary: FEALPy: Finite Element Analysis Library in Python
Home-page: http://github.com/weihuayi/fealpy
Author: Huayi Wei
Author-email: weihuayi@xtu.edu.cn
License: GNU
Requires-Python: >=3.10
Requires-Dist: numpy
Requires-Dist: scipy
Requires-Dist: sympy
Requires-Dist: matplotlib
Requires-Dist: gmsh
Requires-Dist: vtk
Requires-Dist: pyevtk
Requires-Dist: tqdm
Provides-Extra: doc
Requires-Dist: sphinx; extra == "doc"
Requires-Dist: recommonmark; extra == "doc"
Requires-Dist: sphinx-rtd-theme; extra == "doc"
Provides-Extra: dev
Requires-Dist: pytest; extra == "dev"
Requires-Dist: pytest-cov; extra == "dev"
Requires-Dist: bump2version; extra == "dev"
Provides-Extra: optional
Requires-Dist: pypardiso; extra == "optional"
Requires-Dist: pyamg; extra == "optional"
Requires-Dist: mpi4py; extra == "optional"
Requires-Dist: meshpy; extra == "optional"
Dynamic: author
Dynamic: author-email
Dynamic: description
Dynamic: description-content-type
Dynamic: home-page
Dynamic: license
Dynamic: provides-extra
Dynamic: requires-dist
Dynamic: requires-python
Dynamic: summary
